splot/__init__.py
splot/_bk.py
splot/_version.py
splot/_viz_bokeh.py
splot/_viz_esda_mpl.py
splot/_viz_giddy_mpl.py
splot/_viz_libpysal_mpl.py
splot/_viz_utils.py
splot/_viz_value_by_alpha_mpl.py
splot/esda.py
splot/giddy.py
splot/libpysal.py
splot/mapping.py
splot/tests/test_viz_bokeh.py
splot/tests/test_viz_esda_mpl.py
splot/tests/test_viz_giddy_mpl.py
splot/tests/test_viz_libpysal_mpl.py
splot/tests/test_viz_utils.py
splot/tests/test_viz_value_by_alpha_mapl.py
splot-1.1.7.dist-info/LICENSE.txt
splot-1.1.7.dist-info/METADATA
splot-1.1.7.dist-info/WHEEL
splot-1.1.7.dist-info/top_level.txt
splot-1.1.7.dist-info/RECORD
