Metadata-Version: 2.1
Name: splot
Version: 1.1.7
Summary: Visual analytics for spatial analysis with PySAL.
Home-page: https://github.com/pysal/splot
Maintainer: Serge Rey, Stefanie Lumnitz
Maintainer-email: sjsrey@gmail.com, stefanie.lumnitz@gmail.com
License: 3-Clause BSD
Keywords: spatial statistics visualization
Classifier: Development Status :: 5 - Production/Stable
Classifier: Intended Audience :: Science/Research
Classifier: Intended Audience :: Developers
Classifier: Intended Audience :: Education
Classifier: Topic :: Scientific/Engineering
Classifier: Topic :: Scientific/Engineering :: GIS
Classifier: License :: OSI Approved :: BSD License
Classifier: Programming Language :: Python
Classifier: Programming Language :: Python :: 3.8
Classifier: Programming Language :: Python :: 3.9
Classifier: Programming Language :: Python :: 3.10
License-File: LICENSE.txt
Requires-Dist: esda
Requires-Dist: geopandas>=0.9.0
Requires-Dist: giddy
Requires-Dist: libpysal
Requires-Dist: mapclassify
Requires-Dist: matplotlib>=3.3.3
Requires-Dist: numpy
Requires-Dist: packaging
Requires-Dist: seaborn>=0.11.0
Requires-Dist: spreg
Provides-Extra: dev
Requires-Dist: black; extra == "dev"
Requires-Dist: bokeh; extra == "dev"
Requires-Dist: codecov; extra == "dev"
Requires-Dist: coverage; extra == "dev"
Requires-Dist: flake8; extra == "dev"
Requires-Dist: ipywidgets; extra == "dev"
Requires-Dist: isort; extra == "dev"
Requires-Dist: jupyter; extra == "dev"
Requires-Dist: nbconvert; extra == "dev"
Requires-Dist: numpydoc; extra == "dev"
Requires-Dist: pre-commit; extra == "dev"
Requires-Dist: pyflakes; extra == "dev"
Requires-Dist: pytest; extra == "dev"
Requires-Dist: pytest-cov; extra == "dev"
Requires-Dist: sphinx; extra == "dev"
Requires-Dist: sphinx_bootstrap_theme; extra == "dev"
Requires-Dist: sphinxcontrib-bibtex; extra == "dev"
